[
  {
    "dataset_id": "olivetti_faces",
    "method": "umap",
    "n_points": 400,
    "label_type": "ground_truth",
    "meta": {
      "metric": "jaccard",
      "fraction": 0.8,
      "b": 200,
      "tau": 0.8,
      "pairs_per_k": 2000,
      "min_overlap": null,
      "learn_min_overlap": true,
      "min_pairs_M_requested": 1000,
      "min_pairs_M_used": 1000,
      "pairs_total_possible": 19900,
      "pairs_sampled": 2000,
      "m_min": 256,
      "c_implied": 0.9999999999999998,
      "eligible_pairs_count": 1090,
      "overlap_median": 256.0,
      "overlap_iqr": 4.0,
      "max_points": 400,
      "perturbations_frozen_across_k": true,
      "n_null": 200,
      "alpha": 0.05,
      "z_star": 2.0,
      "knife_edge_delta": 0.02,
      "enable_tau_sweep": false
    },
    "k_range": [
      2,
      40
    ],
    "metric": "jaccard",
    "metric_display_name": "Jaccard",
    "perturbations_frozen_across_k": true,
    "m_min": 256,
    "min_overlap_global": 256,
    "c_implied": 0.9999999999999998,
    "pairs_total_possible": 19900,
    "pairs_sampled": 2000,
    "eligible_pairs_count": 1090,
    "min_pairs_M_requested": 1000,
    "min_pairs_M_used": 1000,
    "overlap_median": 256.0,
    "overlap_iqr": 4.0,
    "rep_mean": [
      0.9988273702767764,
      0.6772640408457588
    ],
    "rep_std": [
      0.0048461454308432,
      0.053977268938275966
    ],
    "pairs_used": [
      1090,
      1090
    ],
    "q10": [
      1.0,
      0.6077610422502783
    ],
    "metric_vs_gt_mean": [
      0.030459646348172477,
      0.34747864246507987
    ],
    "metric_vs_gt_std": [
      0.0002567699322505465,
      0.01446723552493337
    ],
    "min_size_mean": [
      64.1,
      3.35
    ],
    "min_size_std": [
      1.5066519173319362,
      0.5894913061275798
    ],
    "median_size_mean": [
      160.0,
      8.0
    ],
    "median_size_std": [
      0.0,
      0.0
    ],
    "max_size_mean": [
      255.9,
      14.915
    ],
    "max_size_std": [
      1.5066519173319362,
      1.7966009573636543
    ],
    "n_small_2_mean": [
      0.0,
      0.04
    ],
    "n_small_2_std": [
      0.0,
      0.19595917942265428
    ],
    "n_small_3_mean": [
      0.0,
      0.875
    ],
    "n_small_3_std": [
      0.0,
      0.8828221791504788
    ],
    "k_eff_mean": [
      1.4714043810738024,
      36.330748290015805
    ],
    "k_eff_std": [
      0.012218540000641893,
      0.6247746241677992
    ],
    "null_mu0": [
      0.5132666698600782,
      0.012270360973516754
    ],
    "null_sigma0": [
      0.00038556160616903774,
      8.614208043361406e-05
    ],
    "z_score": [
      1259.3595748323003,
      7719.730897197492
    ],
    "p_value": [
      0.004975124378109453,
      0.004975124378109453
    ],
    "null_q025": [
      0.5125652492515337,
      0.012114567546098007
    ],
    "null_q975": [
      0.5140005062180175,
      0.01241026697805792
    ],
    "null_q95": [
      0.5138757177610737,
      0.01239867271306069
    ],
    "hat_k_bh": 40,
    "hat_k_z": 40,
    "hat_k_q95": 40,
    "hat_k_q975": 40,
    "bh_found": true,
    "no_significant_k": false,
    "k_min_p": 2,
    "p_min_p": 0.004975124378109453,
    "rep_at_k_min_p": 0.9988273702767764,
    "k_max_z": 40,
    "z_max_z": 7719.730897197492,
    "null_params": {
      "n_null": 200,
      "alpha": 0.05,
      "z_star": 2.0
    },
    "pairwise_metric_vec_by_k": {
      "2": [
        1.0,
        1.0,
        1.0,
        0.9886109870477892,
        1.0,
        1.0,
        1.0,
        1.0,
        1.0,
        1.0,
        1.0,
        0.9551810996265092,
        1.0,
        1.0,
        1.0,
        1.0,
        0.9548444444444445,
        1.0,
        1.0,
        1.0,
        1.0,
        1.0,
        1.0,
        1.0,
        1.0,
        1.0,
        1.0,
        1.0,
        1.0,
        1.0,
        1.0,
        1.0,
        1.0,
        1.0,
        1.0,
        1.0,
        1.0,
        1.0,
        1.0,
        1.0,
        1.0,
        1.0,
        1.0,
        1.0,
        1.0,
        1.0,
        1.0,
        1.0,
        0.9882952354723217,
        1.0,
        1.0,
        1.0,
        1.0,
        1.0,
        0.9887514060742407,
        1.0,
        1.0,
        1.0,
        1.0,
        1.0,
        1.0,
        1.0,
        1.0,
        1.0,
        1.0,
        0.9886897897631509,
        1.0,
        1.0,
        1.0,
        1.0,
        0.988903115663679,
        1.0,
        1.0,
        1.0,
        1.0,
        1.0,
        1.0,
        1.0,
        1.0,
        1.0,
        1.0,
        1.0,
        1.0,
        1.0,
        1.0,
        1.0,
        1.0,
        1.0,
        1.0,
        1.0,
        1.0,
        1.0,
        1.0,
        1.0,
        1.0,
        1.0,
        0.9888071077043683,
        1.0,
        1.0,
        1.0,
        1.0,
        1.0,
        1.0,
        1.0,
        1.0,
        1.0,
        1.0,
        1.0,
        1.0,
        1.0,
        1.0,
        1.0,
        1.0,
        1.0,
        1.0,
        1.0,
        1.0,
        1.0,
        1.0,
        1.0,
        1.0,
        1.0,
        1.0,
        1.0,
        1.0,
        1.0,
        1.0,
        1.0,
        1.0,
        1.0,
        1.0,
        1.0,
        1.0,
        1.0,
        1.0,
        1.0,
        1.0,
        1.0,
        0.9886705611612675,
        1.0,
        1.0,
        1.0,
        1.0,
        1.0,
        1.0,
        1.0,
        1.0,
        1.0,
        1.0,
        1.0,
        1.0,
        1.0,
        1.0,
        1.0,
        1.0,
        1.0,
        1.0,
        1.0,
        1.0,
        1.0,
        1.0,
        1.0,
        1.0,
        1.0,
        1.0,
        1.0,
        1.0,
        1.0,
        1.0,
        1.0,
        0.954661727088295,
        1.0,
        1.0,
        1.0,
        1.0,
        1.0,
        1.0,
        1.0,
        1.0,
        0.98863386052249,
        1.0,
        1.0,
        1.0,
        1.0,
        1.0,
        1.0,
        0.9887684989429175,
        1.0,
        1.0,
        1.0,
        1.0,
        1.0,
        1.0,
        1.0,
        1.0,
        1.0,
        0.9886705611612675,
        1.0,
        1.0,
        1.0,
        1.0,
        1.0,
        1.0,
        1.0,
        1.0,
        1.0,
        1.0,
        1.0,
        1.0,
        1.0,
        1.0,
        1.0,
        0.988496486280829,
        1.0,
        1.0,
        1.0,
        1.0,
        0.9885321100917431,
        1.0,
        1.0,
        1.0,
        1.0,
        1.0,
        1.0,
        1.0,
        0.9887684989429175,
        1.0,
        1.0,
        1.0,
        1.0,
        1.0,
        1.0,
        1.0,
        1.0,
        1.0,
        1.0,
        1.0,
        1.0,
        1.0,
        1.0,
        1.0,
        1.0,
        1.0,
        1.0,
        1.0,
        1.0,
        1.0,
        1.0,
        1.0,
        1.0,
        1.0,
        1.0,
        1.0,
        1.0,
        1.0,
        1.0,
        1.0,
        1.0,
        1.0,
        1.0,
        1.0,
        1.0,
        0.9885235047450894,
        1.0,
        1.0,
        1.0,
        1.0,
        1.0,
        1.0,
        0.9882005899705014,
        1.0,
        0.9887109477553163,
        1.0,
        1.0,
        1.0,
        1.0,
        1.0,
        1.0,
        1.0,
        1.0,
        1.0,
        1.0,
        1.0,
        1.0,
        1.0,
        1.0,
        1.0,
        1.0,
        1.0,
        1.0,
        1.0,
        1.0,
        1.0,
        1.0,
        1.0,
        1.0,
        1.0,
        1.0,
        1.0,
        1.0,
        1.0,
        1.0,
        1.0,
        1.0,
        1.0,
        1.0,
        1.0,
        1.0,
        1.0,
        1.0,
        1.0,
        1.0,
        1.0,
        1.0,
        1.0,
        1.0,
        0.9888272957758584,
        1.0,
        1.0,
        1.0,
        1.0,
        1.0,
        0.988496486280829,
        1.0,
        1.0,
        1.0,
        1.0,
        1.0,
        1.0,
        0.9888458225667528,
        0.9883572857922504,
        0.98863386052249,
        0.9555324855091271,
        1.0,
        1.0,
        1.0,
        1.0,
        1.0,
        1.0,
        1.0,
        1.0,
        1.0,
        1.0,
        1.0,
        1.0,
        1.0,
        1.0,
        1.0,
        1.0,
        1.0,
        1.0,
        1.0,
        1.0,
        1.0,
        1.0,
        1.0,
        1.0,
        1.0,
        1.0,
        1.0,
        1.0,
        1.0,
        1.0,
        1.0,
        1.0,
        1.0,
        1.0,
        1.0,
        1.0,
        1.0,
        1.0,
        1.0,
        1.0,
        1.0,
        1.0,
        1.0,
        1.0,
        1.0,
        1.0,
        1.0,
        1.0,
        1.0,
        1.0,
        1.0,
        1.0,
        1.0,
        1.0,
        1.0,
        1.0,
        1.0,
        1.0,
        1.0,
        1.0,
        1.0,
        1.0,
        1.0,
        1.0,
        1.0,
        1.0,
        1.0,
        1.0,
        0.9887109477553163,
        1.0,
        1.0,
        1.0,
        1.0,
        0.9884356507205132,
        1.0,
        1.0,
        1.0,
        1.0,
        1.0,
        1.0,
        1.0,
        1.0,
        1.0,
        1.0,
        1.0,
        1.0,
        1.0,
        1.0,
        1.0,
        0.9882162661737524,
        1.0,
        1.0,
        1.0,
        1.0,
        0.9884187283132801,
        0.9886585842784513,
        1.0,
        1.0,
        1.0,
        1.0,
        1.0,
        1.0,
        0.9885139985642498,
        1.0,
        1.0,
        1.0,
        1.0,
        1.0,
        1.0,
        1.0,
        1.0,
        1.0,
        1.0,
        1.0,
        1.0,
        1.0,
        0.9887295531289743,
        1.0,
        1.0,
        1.0,
        1.0,
        1.0,
        1.0,
        0.9884632516703786,
        1.0,
        1.0,
        0.9887295531289743,
        1.0,
        1.0,
        1.0,
        1.0,
        1.0,
        1.0,
        1.0,
        1.0,
        1.0,
        1.0,
        1.0,
        1.0,
        0.9884356507205132,
        1.0,
        1.0,
        1.0,
        1.0,
        1.0,
        1.0,
        0.9886897897631509,
        1.0,
        1.0,
        1.0,
        1.0,
        0.9885742230916285,
        1.0,
        1.0,
        1.0,
        1.0,
        1.0,
        1.0,
        1.0,
        1.0,
        1.0,
        1.0,
        1.0,
        1.0,
        1.0,
        1.0,
        1.0,
        1.0,
        1.0,
        1.0,
        1.0,
        1.0,
        1.0,
        1.0,
        1.0,
        1.0,
        1.0,
        0.9888071077043683,
        1.0,
        1.0,
        1.0,
        1.0,
        0.9883742135497401,
        0.9882789249576485,
        1.0,
        1.0,
        0.9885923087206453,
        1.0,
        1.0,
        0.9885321100917431,
        1.0,
        1.0,
        1.0,
        1.0,
        1.0,
        1.0,
        1.0,
        1.0,
        0.9884356507205132,
        1.0,
        1.0,
        1.0,
        1.0,
        1.0,
        1.0,
        1.0,
        0.9883572857922504,
        1.0,
        1.0,
        1.0,
        1.0,
        1.0,
        1.0,
        1.0,
        1.0,
        1.0,
        1.0,
        1.0,
        1.0,
        1.0,
        1.0,
        1.0,
        1.0,
        1.0,
        0.9444444444444444,
        1.0,
        1.0,
        1.0,
        1.0,
        0.9885994913619223,
        1.0,
        1.0,
        1.0,
        1.0,
        0.9884531787719616,
        1.0,
        1.0,
        1.0,
        1.0,
        1.0,
        1.0,
        1.0,
        1.0,
        1.0,
        1.0,
        1.0,
        1.0,
        1.0,
        0.9884632516703786,
        1.0,
        1.0,
        1.0,
        1.0,
        1.0,
        1.0,
        1.0,
        1.0,
        0.9888649115235219,
        1.0,
        1.0,
        1.0,
        1.0,
        1.0,
        1.0,
        1.0,
        1.0,
        1.0,
        1.0,
        1.0,
        1.0,
        1.0,
        0.9540732640787315,
        1.0,
        1.0,
        1.0,
        1.0,
        1.0,
        1.0,
        1.0,
        1.0,
        1.0,
        1.0,
        1.0,
        0.988122303159653,
        1.0,
        1.0,
        1.0,
        1.0,
        1.0,
        1.0,
        1.0,
        1.0,
        1.0,
        1.0,
        1.0,
        1.0,
        1.0,
        1.0,
        1.0,
        1.0,
        1.0,
        1.0,
        1.0,
        1.0,
        1.0,
        1.0,
        1.0,
        1.0,
        1.0,
        1.0,
        1.0,
        0.9885139985642498,
        1.0,
        1.0,
        1.0,
        1.0,
        1.0,
        1.0,
        1.0,
        1.0,
        0.9884356507205132,
        1.0,
        1.0,
        0.9887109477553163,
        1.0,
        1.0,
        1.0,
        1.0,
        1.0,
        1.0,
        1.0,
        0.9884531787719616,
        1.0,
        1.0,
        1.0,
        1.0,
        1.0,
        1.0,
        1.0,
        1.0,
        1.0,
        1.0,
        1.0,
        1.0,
        1.0,
        1.0,
        1.0,
        1.0,
        0.9885398230088496,
        1.0,
        1.0,
        1.0,
        1.0,
        1.0,
        1.0,
        1.0,
        0.9884531787719616,
        0.9885139985642498,
        1.0,
        1.0,
        1.0,
        1.0,
        1.0,
        1.0,
        1.0,
        1.0,
        1.0,
        1.0,
        0.9887487364303609,
        1.0,
        1.0,
        1.0,
        1.0,
        1.0,
        1.0,
        1.0,
        1.0,
        1.0,
        1.0,
        1.0,
        1.0,
        1.0,
        1.0,
        1.0,
        1.0,
        1.0,
        1.0,
        1.0,
        1.0,
        1.0,
        1.0,
        1.0,
        1.0,
        1.0,
        1.0,
        1.0,
        1.0,
        1.0,
        1.0,
        1.0,
        1.0,
        1.0,
        1.0,
        1.0,
        1.0,
        1.0,
        1.0,
        1.0,
        1.0,
        1.0,
        1.0,
        1.0,
        1.0,
        1.0,
        1.0,
        1.0,
        1.0,
        1.0,
        1.0,
        1.0,
        0.9882952354723217,
        1.0,
        1.0,
        1.0,
        1.0,
        1.0,
        1.0,
        1.0,
        1.0,
        1.0,
        1.0,
        0.9885235047450894,
        1.0,
        1.0,
        1.0,
        1.0,
        1.0,
        1.0,
        1.0,
        1.0,
        1.0,
        1.0,
        0.9648741206960385,
        1.0,
        1.0,
        1.0,
        1.0,
        1.0,
        1.0,
        0.9884356507205132,
        1.0,
        1.0,
        1.0,
        1.0,
        0.9882162661737524,
        1.0,
        1.0,
        1.0,
        1.0,
        1.0,
        1.0,
        1.0,
        1.0,
        1.0,
        1.0,
        1.0,
        1.0,
        1.0,
        1.0,
        1.0,
        1.0,
        1.0,
        0.9884531787719616,
        1.0,
        1.0,
        1.0,
        1.0,
        1.0,
        1.0,
        1.0,
        0.9882789249576485,
        0.9887295531289743,
        1.0,
        1.0,
        1.0,
        0.9885139985642498,
        1.0,
        1.0,
        1.0,
        1.0,
        1.0,
        1.0,
        1.0,
        1.0,
        1.0,
        1.0,
        1.0,
        1.0,
        1.0,
        1.0,
        1.0,
        1.0,
        1.0,
        1.0,
        1.0,
        1.0,
        1.0,
        1.0,
        1.0,
        1.0,
        1.0,
        1.0,
        1.0,
        0.9884356507205132,
        1.0,
        1.0,
        0.9884531787719616,
        1.0,
        1.0,
        0.9887109477553163,
        1.0,
        1.0,
        1.0,
        1.0,
        1.0,
        1.0,
        1.0,
        1.0,
        1.0,
        1.0,
        1.0,
        1.0,
        1.0,
        1.0,
        1.0,
        1.0,
        1.0,
        1.0,
        1.0,
        0.9886754649592753,
        1.0,
        1.0,
        0.9885567284662468,
        0.9885398230088496,
        1.0,
        1.0,
        1.0,
        1.0,
        1.0,
        1.0,
        1.0,
        1.0,
        1.0,
        1.0,
        1.0,
        1.0,
        1.0,
        1.0,
        1.0,
        1.0,
        1.0,
        1.0,
        1.0,
        1.0,
        1.0,
        1.0,
        1.0,
        0.9883572857922504,
        1.0,
        1.0,
        1.0,
        1.0,
        1.0,
        1.0,
        1.0,
        1.0,
        1.0,
        1.0,
        1.0,
        1.0,
        1.0,
        1.0,
        1.0,
        1.0,
        1.0,
        1.0,
        1.0,
        1.0,
        1.0,
        1.0,
        1.0,
        1.0,
        1.0,
        1.0,
        1.0,
        1.0,
        1.0,
        1.0,
        1.0,
        1.0,
        1.0,
        1.0,
        1.0,
        1.0,
        1.0,
        0.9882952354723217,
        1.0,
        1.0,
        1.0,
        1.0,
        1.0,
        1.0,
        1.0,
        1.0,
        1.0,
        1.0,
        1.0,
        1.0,
        1.0,
        1.0,
        1.0,
        1.0,
        1.0,
        1.0,
        1.0,
        1.0,
        1.0,
        1.0,
        1.0,
        1.0,
        1.0,
        1.0,
        1.0,
        1.0,
        0.9884356507205132,
        0.9885567284662468,
        1.0,
        1.0,
        1.0,
        0.9545474880329262,
        1.0,
        1.0,
        1.0,
        1.0,
        1.0,
        1.0,
        1.0,
        1.0,
        1.0,
        1.0,
        1.0,
        1.0,
        0.9885742230916285,
        1.0,
        1.0,
        1.0,
        1.0,
        1.0,
        1.0,
        1.0,
        1.0,
        1.0,
        1.0,
        1.0,
        1.0,
        1.0,
        1.0,
        1.0,
        1.0,
        1.0,
        1.0,
        1.0,
        1.0,
        1.0,
        0.9884795713328868,
        1.0,
        1.0,
        1.0,
        1.0,
        1.0,
        1.0,
        1.0,
        0.9886519185764119,
        1.0,
        1.0,
        1.0,
        1.0,
        1.0,
        1.0,
        1.0,
        1.0,
        1.0,
        1.0,
        1.0,
        1.0,
        1.0,
        1.0,
        0.9886897897631509,
        1.0,
        1.0,
        1.0,
        1.0,
        1.0,
        1.0,
        1.0,
        1.0,
        1.0,
        1.0,
        1.0,
        1.0,
        1.0,
        1.0,
        0.9883742135497401,
        1.0,
        1.0,
        0.9886585842784513,
        1.0,
        1.0,
        1.0,
        1.0,
        1.0,
        1.0,
        1.0,
        1.0,
        1.0,
        1.0,
        1.0,
        1.0,
        1.0,
        0.9884024094219186,
        1.0,
        1.0,
        1.0,
        1.0,
        1.0,
        1.0,
        1.0,
        1.0,
        1.0,
        1.0,
        1.0,
        1.0,
        1.0,
        1.0,
        0.9886897897631509,
        1.0,
        1.0,
        1.0,
        1.0,
        0.9886705611612675,
        1.0,
        1.0,
        1.0,
        1.0,
        1.0,
        1.0,
        1.0
      ],
      "40": [
        0.5707410972088547,
        0.5957446808510638,
        0.6374745417515275,
        0.7111834961997828,
        0.6950819672131148,
        0.6100691016781836,
        0.6012024048096193,
        0.680188679245283,
        0.7695800227014756,
        0.6837060702875399,
        0.5940783190066857,
        0.7063655030800822,
        0.6890243902439024,
        0.6356356356356356,
        0.6376195536663124,
        0.740990990990991,
        0.6510204081632653,
        0.7708333333333334,
        0.6849894291754757,
        0.6468716861081655,
        0.6749256689791873,
        0.6159769008662175,
        0.6986006458557589,
        0.6419386745796242,
        0.6526315789473685,
        0.8254335260115607,
        0.6676986584107327,
        0.6484848484848484,
        0.6837256908904811,
        0.6993670886075949,
        0.6190965092402464,
        0.7963163596966414,
        0.662839248434238,
        0.7292759706190975,
        0.5733333333333334,
        0.6864754098360656,
        0.664876476906552,
        0.6951351351351351,
        0.7308510638297873,
        0.6421663442940039,
        0.6653102746693794,
        0.6288167938931297,
        0.7441113490364025,
        0.7283549783549783,
        0.7414529914529915,
        0.6791666666666667,
        0.649390243902439,
        0.7100330760749725,
        0.6642105263157895,
        0.7250755287009063,
        0.6576964477933261,
        0.717607973421927,
        0.66,
        0.6461843409316155,
        0.6494949494949495,
        0.6914103923647932,
        0.6036400404448938,
        0.6807610993657506,
        0.7580993520518359,
        0.5976095617529881,
        0.6967391304347826,
        0.8470319634703196,
        0.6844863731656184,
        0.8023391812865497,
        0.6962809917355371,
        0.7135016465422612,
        0.6622718052738337,
        0.7034339229968782,
        0.694129763130793,
        0.6785329018338727,
        0.6992715920915713,
        0.6717635066258919,
        0.6915322580645161,
        0.7537227949599083,
        0.6771819137749737,
        0.7388392857142857,
        0.6811440677966102,
        0.7142857142857143,
        0.6298507462686567,
        0.7007376185458377,
        0.7218543046357616,
        0.5748031496062992,
        0.697198275862069,
        0.7289029535864979,
        0.6977205153617443,
        0.6082375478927203,
        0.6301775147928994,
        0.646,
        0.7423442449841605,
        0.5845070422535211,
        0.650261780104712,
        0.7141414141414142,
        0.651578947368421,
        0.7058201058201058,
        0.6287367405978785,
        0.6491935483870968,
        0.656701030927835,
        0.6217564870259481,
        0.697928026172301,
        0.7074527252502781,
        0.7670514165792235,
        0.6702014846235419,
        0.5551219512195122,
        0.6987315010570825,
        0.766050054406964,
        0.7464940668824164,
        0.6857142857142857,
        0.6326942482341069,
        0.6243496357960457,
        0.6592517694641051,
        0.6592877767083735,
        0.7230603448275862,
        0.6801181102362205,
        0.8136160714285714,
        0.7357859531772575,
        0.6792645556690501,
        0.7202247191011236,
        0.593186372745491,
        0.6313181367690783,
        0.7209554831704669,
        0.6318840579710145,
        0.6434511434511434,
        0.6923076923076923,
        0.5973360655737705,
        0.5914085914085914,
        0.6549893842887473,
        0.5842583249243188,
        0.6422594142259415,
        0.6061204343534057,
        0.6680080482897385,
        0.7312961011591148,
        0.7838452787258248,
        0.6920762286860582,
        0.5686080947680158,
        0.5337904015670911,
        0.6947141316073355,
        0.6839323467230444,
        0.6826411075612353,
        0.7623126338329764,
        0.6673553719008265,
        0.7731843575418994,
        0.6762513312034079,
        0.7306122448979592,
        0.6272727272727273,
        0.7424714434060229,
        0.7789115646258503,
        0.6276150627615062,
        0.6593406593406593,
        0.7105831533477321,
        0.6676587301587301,
        0.5846007604562737,
        0.6956066945606695,
        0.6455566905005107,
        0.6622851365015167,
        0.6887755102040817,
        0.5714285714285714,
        0.7274633123689728,
        0.6566077003121749,
        0.7917146144994246,
        0.700207468879668,
        0.6407249466950959,
        0.6863157894736842,
        0.6538049303322615,
        0.6424528301886793,
        0.7093023255813954,
        0.6085232903865213,
        0.6722164412070759,
        0.6600209863588667,
        0.7264150943396226,
        0.6874340021119324,
        0.6536144578313253,
        0.6256410256410256,
        0.6866952789699571,
        0.694949494949495,
        0.6360792492179353,
        0.7007454739084132,
        0.6507772020725389,
        0.7356076759061834,
        0.7827510917030568,
        0.5850956696878147,
        0.6332992849846782,
        0.7177334732423925,
        0.6462925851703407,
        0.6526757607555089,
        0.6601441812564367,
        0.6307541625857003,
        0.6518518518518519,
        0.6221562809099901,
        0.677038626609442,
        0.6679802955665025,
        0.6952789699570815,
        0.6160626836434868,
        0.6697819314641744,
        0.6308457711442786,
        0.675,
        0.7609805924412666,
        0.7396963123644251,
        0.7082906857727738,
        0.6617179215270413,
        0.7141403865717192,
        0.6493775933609959,
        0.5856610800744879,
        0.6263959390862944,
        0.6122448979591837,
        0.697286012526096,
        0.6245098039215686,
        0.6468172484599589,
        0.6958817317845829,
        0.735582154515778,
        0.728249194414608,
        0.7320471596998929,
        0.6797927461139897,
        0.7380434782608696,
        0.791095890410959,
        0.6861471861471862,
        0.6710526315789473,
        0.6953367875647668,
        0.6004098360655737,
        0.55859375,
        0.7109704641350211,
        0.6433637284701115,
        0.674074074074074,
        0.7856341189674523,
        0.6848609680741503,
        0.6336633663366337,
        0.7868080094228505,
        0.6890756302521008,
        0.6696035242290749,
        0.7192008879023307,
        0.7365079365079366,
        0.662613981762918,
        0.6361867704280155,
        0.6965020576131687,
        0.7061965811965812,
        0.7894736842105263,
        0.6438775510204081,
        0.6673532440782698,
        0.6877005347593583,
        0.6015037593984962,
        0.6153846153846154,
        0.6653465346534654,
        0.630346232179226,
        0.6246276067527309,
        0.6890052356020943,
        0.6978947368421052,
        0.6146245059288538,
        0.7207859358841778,
        0.7539325842696629,
        0.6921487603305785,
        0.7179763186221744,
        0.7980241492864983,
        0.64576802507837,
        0.6306584362139918,
        0.6151484135107472,
        0.658835546475996,
        0.6519959058341863,
        0.7213290460878885,
        0.627254509018036,
        0.6117533718689788,
        0.6062437059415912,
        0.6118811881188119,
        0.7834602829162133,
        0.6459816887080366,
        0.716842105263158,
        0.7843359818388195,
        0.6213991769547325,
        0.6837349397590361,
        0.7066950053134963,
        0.7133333333333334,
        0.799081515499426,
        0.8063112078346029,
        0.7101604278074867,
        0.6279761904761905,
        0.6801275239107333,
        0.558206106870229,
        0.6370070778564206,
        0.7071129707112971,
        0.6687054026503568,
        0.6771819137749737,
        0.7425531914893617,
        0.6902748414376322,
        0.6561546286876907,
        0.6870611835506519,
        0.6160896130346232,
        0.7638136511375948,
        0.6670190274841438,
        0.6635610766045549,
        0.7303128371089536,
        0.6281156530408774,
        0.6919831223628692,
        0.7336898395721925,
        0.711038961038961,
        0.8070175438596491,
        0.6121031746031746,
        0.731048805815161,
        0.8195819581958196,
        0.6466466466466466,
        0.7317596566523605,
        0.6569709127382146,
        0.6412940057088488,
        0.6922257720979765,
        0.6454918032786885,
        0.7297297297297297,
        0.6306584362139918,
        0.585838991270611,
        0.7118463180362861,
        0.7414330218068536,
        0.6721144024514811,
        0.7291220556745182,
        0.5826923076923077,
        0.6244855967078189,
        0.7167755991285403,
        0.6870967741935484,
        0.6487562189054726,
        0.5951219512195122,
        0.6919831223628692,
        0.647117296222664,
        0.7737556561085973,
        0.6159274193548387,
        0.6113402061855671,
        0.6993736951983298,
        0.7317813765182186,
        0.7472283813747228,
        0.721868365180467,
        0.5764235764235764,
        0.674468085106383,
        0.635814889336016,
        0.6702241195304163,
        0.7331189710610932,
        0.6817713697219362,
        0.7041800643086816,
        0.7435064935064936,
        0.6663306451612904,
        0.7164502164502164,
        0.6539649845520082,
        0.7350157728706624,
        0.6917372881355932,
        0.6618106139438086,
        0.7053763440860215,
        0.7583892617449665,
        0.6794871794871795,
        0.5905432595573441,
        0.6434343434343435,
        0.677038626609442,
        0.6095820591233435,
        0.6688034188034188,
        0.6528758829465187,
        0.6906906906906907,
        0.7838137472283814,
        0.7235421166306696,
        0.7483870967741936,
        0.8147295742232451,
        0.7107438016528925,
        0.7007616974972797,
        0.6815217391304348,
        0.6031434184675835,
        0.6164241164241164,
        0.5833333333333334,
        0.6970362239297475,
        0.6209677419354839,
        0.6356275303643725,
        0.6442762535477767,
        0.6227979274611399,
        0.7192224622030238,
        0.6640159045725647,
        0.6724845995893224,
        0.6980351602895554,
        0.5874620829120324,
        0.7013669821240799,
        0.7037037037037037,
        0.700312174817898,
        0.6405767250257467,
        0.6202783300198808,
        0.6965442764578834,
        0.6541666666666667,
        0.6710130391173521,
        0.7098831030818279,
        0.6049129989764586,
        0.5712927756653993,
        0.6367226061204343,
        0.7291440953412784,
        0.7131696428571429,
        0.7001114827201784,
        0.6846388606307223,
        0.7440347071583514,
        0.747872340425532,
        0.7004357298474946,
        0.6652542372881356,
        0.6988577362409139,
        0.6581632653061225,
        0.6328600405679513,
        0.7183257918552036,
        0.6051332675222113,
        0.6752049180327869,
        0.6763440860215054,
        0.6923076923076923,
        0.7584388185654009,
        0.6952479338842975,
        0.7231578947368421,
        0.7081081081081081,
        0.7745098039215687,
        0.7040923399790137,
        0.6025267249757046,
        0.7306034482758621,
        0.643756050338819,
        0.6399176954732511,
        0.7282728272827282,
        0.6834532374100719,
        0.6954689146469969,
        0.6438213914849429,
        0.6350435624394967,
        0.5726915520628684,
        0.7039473684210527,
        0.7823779193205945,
        0.7414684591520165,
        0.6793422404933196,
        0.5993945509586277,
        0.5603864734299517,
        0.6851851851851852,
        0.6143277723258096,
        0.5928205128205128,
        0.6559139784946236,
        0.6080402010050251,
        0.6821392532795156,
        0.6264705882352941,
        0.7199582027168234,
        0.7197452229299363,
        0.7366167023554604,
        0.6629554655870445,
        0.7041123370110332,
        0.6987115956392468,
        0.6918238993710691,
        0.6629098360655737,
        0.6283643892339544,
        0.5676470588235294,
        0.6976016684045881,
        0.8017718715393134,
        0.6955128205128205,
        0.8428731762065096,
        0.6507430997876857,
        0.7148846960167715,
        0.6832971800433839,
        0.7853107344632768,
        0.6183282980866063,
        0.746524064171123,
        0.6042726347914548,
        0.6575481256332321,
        0.7242128121606949,
        0.6138917262512769,
        0.6316326530612245,
        0.7111834961997828,
        0.7026143790849673,
        0.6698412698412698,
        0.6898002103049422,
        0.6766766766766766,
        0.6342494714587738,
        0.6328986960882648,
        0.6718903036238981,
        0.6714285714285714,
        0.6212121212121212,
        0.5723622782446312,
        0.6676737160120846,
        0.6036468330134357,
        0.6957928802588996,
        0.6113320079522863,
        0.6887486855941115,
        0.7182795698924731,
        0.5718363463368221,
        0.6822916666666666,
        0.6208333333333333,
        0.7444444444444445,
        0.7165948275862069,
        0.6002034587995931,
        0.7466666666666667,
        0.6305015353121801,
        0.7132034632034632,
        0.6442495126705653,
        0.5807086614173228,
        0.6062683643486778,
        0.6586638830897703,
        0.7158351409978309,
        0.7061266874350987,
        0.6021717670286278,
        0.6779835390946503,
        0.6846388606307223,
        0.6892039258451472,
        0.66524064171123,
        0.6171717171717171,
        0.5603448275862069,
        0.7775401069518717,
        0.6821256038647343,
        0.7341101694915254,
        0.66798810703667,
        0.7289220917822838,
        0.6976744186046512,
        0.75,
        0.6625766871165644,
        0.602510460251046,
        0.6260245901639344,
        0.722707423580786,
        0.5741811175337187,
        0.6927083333333334,
        0.7491995731056563,
        0.7166156982670744,
        0.6992481203007519,
        0.6574257425742575,
        0.6880733944954128,
        0.6094210009813543,
        0.7,
        0.6832358674463938,
        0.693446088794926,
        0.7355110642781876,
        0.6942740286298569,
        0.7007534983853606,
        0.6157587548638133,
        0.7441860465116279,
        0.6328600405679513,
        0.7213290460878885,
        0.6575052854122622,
        0.7100213219616205,
        0.8161057692307693,
        0.634020618556701,
        0.5812379110251451,
        0.5903257650542941,
        0.7412031782065834,
        0.7965714285714286,
        0.6194251734390486,
        0.6768421052631579,
        0.6918918918918919,
        0.5854616895874263,
        0.7211538461538461,
        0.6988082340195017,
        0.7112299465240641,
        0.7076086956521739,
        0.6868475991649269,
        0.7257709251101322,
        0.6731358529111338,
        0.6289370078740157,
        0.6405767250257467,
        0.6957470010905126,
        0.7144396551724138,
        0.5981688708036622,
        0.705685618729097,
        0.6488469601677149,
        0.6412289395441031,
        0.6513761467889908,
        0.6199186991869918,
        0.7991021324354658,
        0.6694045174537988,
        0.6386554621848739,
        0.7435098650051921,
        0.676954732510288,
        0.700218818380744,
        0.6873661670235546,
        0.6062124248496994,
        0.6413155190133607,
        0.7174603174603175,
        0.78125,
        0.684156378600823,
        0.6122860020140987,
        0.6124497991967871,
        0.6032388663967612,
        0.7264864864864865,
        0.6153846153846154,
        0.6299694189602446,
        0.698249227600412,
        0.7107790821771611,
        0.7209051724137931,
        0.6420737786640079,
        0.69989281886388,
        0.6561546286876907,
        0.6900647948164147,
        0.7079918032786885,
        0.7057522123893806,
        0.7055084745762712,
        0.7295864262990456,
        0.6358866736621196,
        0.6849173553719008,
        0.6214355948869223,
        0.7455947136563876,
        0.6032225579053374,
        0.6227897838899804,
        0.6779303062302007,
        0.8156359393232205,
        0.6327739387956565,
        0.6420118343195266,
        0.714765100671141,
        0.7150715071507151,
        0.730299667036626,
        0.6367076631977294,
        0.687693898655636,
        0.6192468619246861,
        0.6447638603696099,
        0.6562162162162162,
        0.8244803695150116,
        0.7098560354374308,
        0.6128404669260701,
        0.6258776328986961,
        0.7046908315565032,
        0.7072916666666667,
        0.7262569832402235,
        0.6348088531187123,
        0.6601842374616171,
        0.6722772277227723,
        0.6537678207739308,
        0.6430738119312437,
        0.62970498474059,
        0.6705756929637526,
        0.7253886010362695,
        0.6613588110403397,
        0.6982310093652445,
        0.6821052631578948,
        0.5954724409448819,
        0.622093023255814,
        0.6781725888324873,
        0.6293193717277487,
        0.6536842105263158,
        0.7067099567099567,
        0.6935312831389183,
        0.7236286919831224,
        0.7184154175588865,
        0.7532894736842105,
        0.71,
        0.598605577689243,
        0.7663344407530454,
        0.577490774907749,
        0.6170854271356784,
        0.6495278069254984,
        0.6782231852654388,
        0.7318435754189944,
        0.7525539160045402,
        0.6196377502383222,
        0.7331887201735358,
        0.6897297297297297,
        0.6814734561213435,
        0.6160164271047228,
        0.6061538461538462,
        0.599,
        0.6837513631406761,
        0.6517205422314911,
        0.6769394261424017,
        0.7248394004282656,
        0.710352422907489,
        0.7227319062181448,
        0.7078534031413612,
        0.6175580221997982,
        0.7244582043343654,
        0.5545023696682464,
        0.618848167539267,
        0.7104984093319194,
        0.7948430493273543,
        0.6777546777546778,
        0.6210739614994935,
        0.7284768211920529,
        0.6505905511811023,
        0.6209598432908913,
        0.7377584330794341,
        0.6306930693069307,
        0.6606786427145709,
        0.6477157360406092,
        0.7059436913451512,
        0.590513068731849,
        0.5968841285296982,
        0.6555323590814196,
        0.8229777256740914,
        0.6463917525773196,
        0.7199570815450643,
        0.6537282941777324,
        0.625748502994012,
        0.7210031347962382,
        0.6652542372881356,
        0.6422110552763819,
        0.6460268317853457,
        0.5741626794258373,
        0.7351648351648352,
        0.7034764826175869,
        0.6117886178861789,
        0.6846846846846847,
        0.6743940990516333,
        0.6548117154811716,
        0.6563467492260062,
        0.6798748696558915,
        0.7663344407530454,
        0.7288317256162915,
        0.6023856858846919,
        0.6795154185022027,
        0.6831896551724138,
        0.6928645294725957,
        0.6523046092184369,
        0.7443946188340808,
        0.6906552094522019,
        0.8004459308807135,
        0.7664473684210527,
        0.7180851063829787,
        0.6763440860215054,
        0.6251207729468599,
        0.6676676676676677,
        0.7014028056112225,
        0.7094017094017094,
        0.8374269005847953,
        0.7156348373557188,
        0.7296996662958843,
        0.6875687568756875,
        0.6307385229540918,
        0.5563041385948027,
        0.6776519052523172,
        0.6176176176176176,
        0.6815352697095436,
        0.6794208893485005,
        0.6387225548902196,
        0.6382536382536382,
        0.6597077244258872,
        0.6750261233019854,
        0.6728778467908902,
        0.7573449401523396,
        0.6709129511677282,
        0.6713426853707415,
        0.6529100529100529,
        0.6478578892371996,
        0.6647230320699709,
        0.7505543237250555,
        0.6767151767151767,
        0.6635416666666667,
        0.6477157360406092,
        0.6264189886480909,
        0.7048503611971104,
        0.6474820143884892,
        0.5925553319919518,
        0.7415349887133182,
        0.6763754045307443,
        0.677720207253886,
        0.6663101604278074,
        0.6352201257861635,
        0.654196157735086,
        0.6196377502383222,
        0.6141975308641975,
        0.6519114688128773,
        0.7373519913885899,
        0.6238894373149062,
        0.7001090512540894,
        0.6814345991561181,
        0.683248730964467,
        0.6739367502726281,
        0.5949119373776908,
        0.653125,
        0.7413612565445026,
        0.6984435797665369,
        0.6926406926406926,
        0.6618705035971223,
        0.6919786096256685,
        0.7096069868995634,
        0.6730382293762576,
        0.7145790554414785,
        0.6776947705442903,
        0.6007984031936128,
        0.6215139442231076,
        0.587426326129666,
        0.7656765676567657,
        0.7683982683982684,
        0.6327800829875518,
        0.7135135135135136,
        0.6476091476091476,
        0.6449704142011834,
        0.5871212121212122,
        0.6217516843118384,
        0.6515463917525773,
        0.6492307692307693,
        0.6687179487179488,
        0.723952738990333,
        0.6638830897703549,
        0.6337448559670782,
        0.799781181619256,
        0.7279569892473118,
        0.6829268292682927,
        0.6421725239616614,
        0.7521645021645021,
        0.7161290322580646,
        0.7222832052689352,
        0.7697368421052632,
        0.621676891615542,
        0.6572295247724975,
        0.7425641025641025,
        0.7056277056277056,
        0.7305585980284776,
        0.6717791411042945,
        0.7192429022082019,
        0.6616161616161617,
        0.671875,
        0.7907239819004525,
        0.6785714285714286,
        0.6944723618090453,
        0.7323651452282157,
        0.6750524109014675,
        0.6629554655870445,
        0.5952868852459017,
        0.6470588235294118,
        0.6133866133866134,
        0.766050054406964,
        0.607707509881423,
        0.675365344467641,
        0.7182095625635809,
        0.6315280464216635,
        0.7001078748651565,
        0.721030042918455,
        0.6902286902286903,
        0.6659574468085107,
        0.6380558428128231,
        0.667379679144385,
        0.5646836638338055,
        0.7186147186147186,
        0.6098522167487684,
        0.6307692307692307,
        0.6158475426278837,
        0.7849099099099099,
        0.609,
        0.662217659137577,
        0.654042988741044,
        0.7334669338677354,
        0.6813304721030042,
        0.6912539515279241,
        0.6666666666666666,
        0.5812379110251451,
        0.6965226554267651,
        0.657563025210084,
        0.6908904810644831,
        0.6411075612353567,
        0.6791845493562232,
        0.6705020920502092,
        0.6028708133971292,
        0.7456896551724138,
        0.6075050709939148,
        0.6915983606557377,
        0.7640966628308401,
        0.712882096069869,
        0.6862745098039216,
        0.6305263157894737,
        0.6920668058455115,
        0.5885947046843177,
        0.6908893709327549,
        0.6437125748502994,
        0.6683778234086243,
        0.672322375397667,
        0.6841584158415842,
        0.6392785571142284,
        0.706441393875396,
        0.6870967741935484,
        0.6820987654320988,
        0.6773162939297125,
        0.7302631578947368,
        0.6748663101604279,
        0.6774869109947644,
        0.7225186766275347,
        0.7483801295896328,
        0.6292481977342945,
        0.7235169491525424,
        0.7161016949152542,
        0.7605633802816901,
        0.6401590457256461,
        0.676378772112383,
        0.7378531073446327,
        0.6763440860215054,
        0.8084606345475911,
        0.7076761303890642,
        0.7239915074309978,
        0.5521951219512196,
        0.6635416666666667,
        0.6233502538071066,
        0.7226277372262774,
        0.6434782608695652,
        0.6483971044467425,
        0.6205533596837944,
        0.6327345309381237,
        0.6894343649946638,
        0.8044943820224719,
        0.6960081883316275,
        0.7872340425531915,
        0.7489451476793249,
        0.706441393875396,
        0.6835051546391753,
        0.7111356119073869,
        0.7539325842696629,
        0.6970684039087948,
        0.6691253951527925,
        0.7207505518763797,
        0.6228686058174524,
        0.5829145728643216,
        0.6560574948665298,
        0.6812705366922235,
        0.5906838453914767,
        0.6606243705941591,
        0.7912457912457912,
        0.7121046892039259,
        0.6591576885406464,
        0.6680628272251309,
        0.6342182890855457,
        0.7295173961840629,
        0.6281661600810537,
        0.6179196704428425,
        0.7225305216426193,
        0.6652719665271967,
        0.7122692725298588,
        0.7602663706992231,
        0.7259668508287292,
        0.6652719665271967,
        0.5950248756218905,
        0.6815816857440167,
        0.6522613065326633,
        0.6938997821350763,
        0.7367256637168141,
        0.6597510373443983,
        0.6722513089005235,
        0.6812749003984063,
        0.7675438596491229,
        0.583,
        0.6695095948827292,
        0.7004132231404959,
        0.6051660516605166,
        0.7263157894736842,
        0.7611630321910696,
        0.6329243353783232,
        0.7337662337662337,
        0.6309148264984227,
        0.7176220806794055,
        0.6032977691561591,
        0.6991434689507494,
        0.616580310880829,
        0.7444326617179216,
        0.677710843373494,
        0.7070914696813977,
        0.7811816192560175,
        0.6970021413276232,
        0.7526539278131635,
        0.701212789415656,
        0.5764362220058422,
        0.6287487073422957,
        0.7291666666666666,
        0.6142131979695431,
        0.7238095238095238,
        0.5887573964497042,
        0.731359649122807,
        0.6576763485477178,
        0.6448780487804878,
        0.6241276171485544,
        0.6179104477611941,
        0.8434684684684685,
        0.7168141592920354,
        0.6620320855614973,
        0.7059436913451512,
        0.6652542372881356,
        0.6779846659364732,
        0.7272727272727273,
        0.7184873949579832,
        0.6645702306079665,
        0.6871686108165429,
        0.6713819368879217,
        0.6596558317399618,
        0.6994871794871795,
        0.609805924412666,
        0.5932367149758454,
        0.6767895878524945,
        0.6071065989847716,
        0.6560319042871385,
        0.6568047337278107,
        0.7277599142550911,
        0.5789473684210527,
        0.7937915742793792,
        0.6627534685165422,
        0.6813880126182965,
        0.6983122362869199,
        0.6170421155729677,
        0.6174089068825911,
        0.694006309148265,
        0.7120901639344263,
        0.6723404255319149,
        0.6432264736297828,
        0.7465535524920467,
        0.7217484008528785,
        0.6865828092243187,
        0.6591375770020534,
        0.7031914893617022,
        0.65625,
        0.6788990825688074,
        0.6589769307923772,
        0.6123876123876124,
        0.704239917269907,
        0.6285414480587618,
        0.6077669902912621,
        0.6080550098231827,
        0.6723809523809524,
        0.703205791106515,
        0.6597938144329897,
        0.6990972918756269,
        0.6374207188160677,
        0.6360917248255235,
        0.7074468085106383,
        0.5679133858267716,
        0.6288032454361054,
        0.7031578947368421,
        0.6194174757281553,
        0.6617063492063492,
        0.6561844863731656,
        0.6109979633401222,
        0.732824427480916,
        0.6016016016016016,
        0.6578389830508474,
        0.7419700214132763,
        0.6273538156590683,
        0.7381974248927039,
        0.7494456762749445,
        0.7001078748651565,
        0.6869009584664537,
        0.721868365180467,
        0.7183246073298429,
        0.725,
        0.6394279877425945,
        0.6775553213909379,
        0.7588571428571429,
        0.6571428571428571,
        0.6308360477741585,
        0.6563745019920318,
        0.6036585365853658,
        0.6757322175732218,
        0.6870466321243524,
        0.6363636363636364,
        0.6473029045643154,
        0.7382478632478633,
        0.5851162790697675,
        0.770949720670391,
        0.7183544303797469,
        0.6798378926038501,
        0.758082497212932,
        0.6959183673469388,
        0.6041666666666666,
        0.688034188034188,
        0.6753112033195021,
        0.6001994017946162,
        0.6712184873949579,
        0.6878147029204431,
        0.6882978723404255,
        0.7377398720682303,
        0.6209912536443148,
        0.664218258132214,
        0.5935984481086324,
        0.6736318407960199,
        0.6323529411764706,
        0.6723044397463002,
        0.7254685777287762,
        0.7616525423728814,
        0.7201225740551583,
        0.7796234772978959,
        0.5972350230414747,
        0.6904255319148936,
        0.7013129102844639,
        0.7121374865735768,
        0.5694716242661448,
        0.6772823779193206,
        0.7062256809338522,
        0.6558704453441295,
        0.6652631578947369,
        0.6475903614457831,
        0.6970649895178197,
        0.6909448818897638,
        0.8105975197294251,
        0.7079646017699115,
        0.7368421052631579,
        0.6706008583690987,
        0.7375964718853363,
        0.6441176470588236,
        0.7315731573157316,
        0.7268817204301076,
        0.6215098241985523,
        0.6187563710499491,
        0.6118488253319714,
        0.5631528964862298,
        0.6774530271398748,
        0.7129237288135594,
        0.5902912621359223,
        0.7179203539823009,
        0.7296137339055794,
        0.5817120622568094,
        0.7030114226375909,
        0.7460148777895855,
        0.6279306829765545,
        0.6474164133738601,
        0.6212590299277606,
        0.644927536231884,
        0.7176350662589195,
        0.6826722338204593,
        0.5582761998041136,
        0.6648879402347919
      ]
    },
    "hat_k": 40,
    "hat_k_tau": null,
    "hat_k_consec": null,
    "cap_hit": true,
    "knife_edge": false,
    "hat_k_tau075": null,
    "hat_k_tau080": null,
    "hat_k_tau085": null,
    "p_at_hat_bh": 0.004975124378109453,
    "z_at_hat_bh": 7719.730897197492,
    "rep_at_hat_bh": 0.6772640408457588,
    "k_eff_at_hat": 36.330748290015805,
    "min_size_at_hat": 3.35,
    "n_small_2_at_hat": 0.04,
    "degenerate_at_hat": true
  }
]